README.md
setup.py
flexidate/__init__.py
flexidate/test_flexidate.py
flexidate.egg-info/PKG-INFO
flexidate.egg-info/SOURCES.txt
flexidate.egg-info/dependency_links.txt
flexidate.egg-info/not-zip-safe
flexidate.egg-info/requires.txt
flexidate.egg-info/top_level.txt