Metadata-Version: 1.1
Name: flexidate
Version: 1.4
Summary: Very flexible date parsing and normalization utilities
Home-page: http://github.com/okfn/flexidate/
Author: Open Knowledge Foundation
Author-email: info@okfn.org
License: MIT
Platform: UNKNOWN
Classifier: Development Status :: 5 - Production/Stable
Classifier: Environment :: Console
Classifier: Intended Audience :: Developers
Classifier: Operating System :: OS Independent
Classifier: Programming Language :: Python :: 2.7
Classifier: Programming Language :: Python :: 3.3
Classifier: Programming Language :: Python :: 3.4
Classifier: Programming Language :: Python :: 3.5
Classifier: Topic :: Software Development :: Libraries :: Python Modules
